{
  "items": [
    {
      "sourceCode": "PER_ADAMCROW63_AT_GMAILCOM",
      "targetCode": "PER_ADAMCROW63_AT_GMAILCOM",
      "questionCode": "QUE_SEARCH_GRP",
      "attributeCode": "QQQ_QUESTION_GROUP",
      "mandatory": false,
      "oneshot": false,
      "disabled": false,
      "hidden": false,
      "readonly": false,
      "weight": 0.0,
      "parentId": 0,
      "childAsks": [
        {
          "question": {
            "attribute": {
              "dataType": {
                "className": "Text",
                "typeName": "Text",
                "validationList": [
                ]
              },
              "defaultPrivacyFlag": false,
              "code": "PRI_SEARCH_CONTENT",
              "index": 0,
              "created": "2019-02-10T10:41:00",
              "updated": "2019-02-10T10:41:00",
              "id": 159,
              "name": "Name",
              "realm": "genny"
            },
            "attributeCode": "PRI_SEARCH_CONTENT",
            "mandatory": false,
            "readonly": false,
            "oneshot": false,
            "placeholder": "Search Internmatch",
            "code": "QUE_SEARCH_BASIC",
            "index": 0,
            "created": "2018-08-14T02:46:55",
            "updated": "2018-10-04T23:29:15",
            "id": 88,
            "name": "Search Content",
            "realm": "genny"
          },
          "sourceCode": "PER_ADAMCROW63_AT_GMAILCOM",
          "targetCode": "PER_ADAMCROW63_AT_GMAILCOM",
          "questionCode": "QUE_SEARCH_BASIC",
          "attributeCode": "PRI_SEARCH_CONTENT",
          "mandatory": true,
          "oneshot": false,
          "disabled": false,
          "hidden": false,
          "readonly": false,
          "weight": 0.0,
          "parentId": 0,
          "contextList": {
            "contexts": [
              {
                "contextCode": "THM_VISUAL_CONTROL_SEARCH",
                "created": "2019-02-06T04:24:58",
                "name": "THEME",
                "realm": "genny",
                "weight": 1
              },
              {
                "contextCode": "THM_VISUAL_CONTROL_SEARCH_ICON",
                "created": "2019-02-06T04:24:58",
                "visualControlType": "ICON",
                "name": "THEME",
                "realm": "genny",
                "weight": 1
              },
              {
                "contextCode": "THM_BACKGROUND_WHITE",
                "created": "2019-02-06T04:24:58",
                "name": "THEME",
                "value": "WRAPPER",
                "realm": "genny",
                "weight": 1
              }
            ]
          },
          "created": "2018-08-29T03:00:40",
          "updated": "2018-12-12T02:22:33",
          "id": 3668,
          "name": "First Name",
          "realm": "genny"
        }
      ],
      "contextList": {
      },
      "created": "2019-02-14T03:15:22",
      "id": 46341,
      "name": "Search Group",
      "realm": "genny"
    }
  ],
  "data_type": "Ask",
  "delete": false,
  "replace": false,
  "msg_type": "DATA_MSG"
}